{
    "date": "2025-05-09T22:05:12.859361",
    "daily_trade_count": 2,
    "daily_pnl": 0.0,
    "last_trade_time": "2025-05-09T22:05:12.859361",
    "trades_history": [
        {
            "time": "2025-05-09T08:47:59.201869",
            "symbol": "SOLUSDT",
            "side": "buy",
            "amount": 1.0,
            "price": 174.12,
            "stop_loss": 172.0,
            "take_profit": 176.0,
            "leverage": 5,
            "margin_mode": "isolated",
            "post_only": false,
            "order_id": "173584235516"
        },
        {
            "time": "2025-05-09T22:05:12.859361",
            "symbol": "SOLUSDT",
            "side": "buy",
            "amount": 1.0,
            "price": 171.8,
            "stop_loss": 170.0,
            "take_profit": 172.0,
            "leverage": 50,
            "margin_mode": "isolated",
            "post_only": false,
            "order_id": "173627210471"
        }
    ]
}